home/al/.config/systemd/user/raspisump.service
home/al/.config/systemd/user/rsumpwebchart.service
home/al/.config/systemd/user/rsumpwebchart.timer
home/al/raspi-sump/VERSION
home/al/raspi-sump/charts/README.md
home/al/raspi-sump/cron/README.md
home/al/raspi-sump/cron/picrontab
home/al/raspi-sump/csv/README.md
home/al/raspi-sump/docs/README.md
home/al/raspi-sump/docs/install.md
home/al/raspi-sump/logs/README.md
home/al/raspi-sump/sample_config/raspisump.conf
home/al/raspi-sump/web/index.html
home/al/raspi-sump/web/css/includes.js
home/al/raspi-sump/web/css/index.html
home/al/raspi-sump/web/css/raspi.css
home/al/raspi-sump/web/css/inc/VERSION
home/al/raspi-sump/web/images/logo.png
raspisump/__init__.py
raspisump/alerts.py
raspisump/checkpid.py
raspisump/config_values.py
raspisump/emailtest.py
raspisump/heartbeat.py
raspisump/log.py
raspisump/reading.py
raspisump/todaychart.py
raspisump/webchart.py
raspisump-1.9.4.data/scripts/emailtest
raspisump-1.9.4.data/scripts/rsump.py
raspisump-1.9.4.data/scripts/rsumpchart.py
raspisump-1.9.4.data/scripts/rsumpmonitor.py
raspisump-1.9.4.data/scripts/rsumpsupport
raspisump-1.9.4.data/scripts/rsumpwebchart.py
raspisump-1.9.4.dist-info/LICENSE
raspisump-1.9.4.dist-info/METADATA
raspisump-1.9.4.dist-info/WHEEL
raspisump-1.9.4.dist-info/top_level.txt
raspisump-1.9.4.dist-info/RECORD
