Metadata-Version: 2.1
Name: raspisump
Version: 1.9.4
Summary: A sump pit monitoring system for Raspberry Pi
Home-page: https://www.linuxnorth.org/raspi-sump/
Download-URL: https://github.com/alaudet/raspi-sump/releases
Author: Al Audet
Author-email: alaudet@linuxnorth.org
License: MIT License
Classifier: Development Status :: 5 - Production/Stable
Classifier: Environment :: Console
Classifier: Intended Audience :: End Users/Desktop
Classifier: Natural Language :: English
Classifier: Operating System :: POSIX :: Linux
Classifier: Programming Language :: Python :: 3.7
Classifier: Programming Language :: Python :: 3.9
Classifier: Topic :: Home Automation
Classifier: License :: OSI Approved :: MIT License
License-File: LICENSE
Requires-Dist: hcsr04sensor >=1.7
